chaosgce/__init__.py
chaosgce/types.py
chaosgce/nodepool/__init__.py
chaosgce/nodepool/actions.py
chaostoolkit_google_cloud-0.2.3.dist-info/LICENSE
chaostoolkit_google_cloud-0.2.3.dist-info/METADATA
chaostoolkit_google_cloud-0.2.3.dist-info/WHEEL
chaostoolkit_google_cloud-0.2.3.dist-info/top_level.txt
chaostoolkit_google_cloud-0.2.3.dist-info/RECORD
