Metadata-Version: 2.1
Name: chaostoolkit-google-cloud
Version: 0.2.3
Summary: Chaos Toolkit Extension for Google Cloud Engine
Home-page: http://chaostoolkit.org
Author: chaostoolkit Team
Author-email: contact@chaostoolkit.org
License: Apache License Version 2.0
Platform: UNKNOWN
Classifier: Development Status :: 4 - Beta
Classifier: Intended Audience :: Developers
Classifier: License :: Freely Distributable
Classifier: Operating System :: OS Independent
Classifier: License :: OSI Approved :: Apache Software License
Classifier: Programming Language :: Python
Classifier: Programming Language :: Python :: 3
Classifier: Programming Language :: Python :: 3.5
Classifier: Programming Language :: Python :: 3.6
Classifier: Programming Language :: Python :: Implementation
Classifier: Programming Language :: Python :: Implementation :: CPython
Requires-Python: >=3.5.*
Requires-Dist: chaostoolkit-lib (>=0.16.0)
Requires-Dist: chaostoolkit-kubernetes (>=0.15.0)
Requires-Dist: google-auth
Requires-Dist: google-auth-httplib2
Requires-Dist: google-api-python-client
Requires-Dist: logzero
